yt_music_manager_cli/__init__.py
yt_music_manager_cli/__main__.py
yt_music_manager_cli/cli.py
yt_music_manager_cli/config.py
yt_music_manager_cli/console_utils.py
yt_music_manager_cli/download_manager.py
yt_music_manager_cli/exceptions.py
yt_music_manager_cli/logging_utils.py
yt_music_manager_cli/oauth_client_config.py
yt_music_manager_cli/oauth_flow.py
yt_music_manager_cli/oauth_handler.py
yt_music_manager_cli/oauth_security.py
yt_music_manager_cli/playlist_manager.py
yt_music_manager_cli/sync_engine.py
yt_music_manager_cli/unified_youtube_client.py
yt_music_manager_cli/youtube_api.py
yt_music_manager_cli/youtube_extractor.py
yt_music_manager_cli/data/oauth_client_bundled.json
yt_music_manager_cli-1.0.2.dist-info/licenses/LICENSE
yt_music_manager_cli-1.0.2.dist-info/METADATA
yt_music_manager_cli-1.0.2.dist-info/WHEEL
yt_music_manager_cli-1.0.2.dist-info/entry_points.txt
yt_music_manager_cli-1.0.2.dist-info/top_level.txt
yt_music_manager_cli-1.0.2.dist-info/RECORD
