Metadata-Version: 2.4
Name: yt-music-manager-cli
Version: 1.0.2
Summary: A production-ready YouTube music playlist manager and synchronizer (YT Music Manager CLI)
Author-email: Sukarth Acharya <sukarthacharya@gmail.com>
License: MIT
Project-URL: Homepage, https://github.com/sukarth/yt-music-manager-cli
Project-URL: Bug Reports, https://github.com/sukarth/yt-music-manager-cli/issues
Project-URL: Source, https://github.com/sukarth/yt-music-manager-cli
Project-URL: Privacy Policy, https://github.com/sukarth/yt-music-manager-cli/blob/main/PRIVACY_POLICY.md
Classifier: Development Status :: 5 - Production/Stable
Classifier: Intended Audience :: End Users/Desktop
Classifier: License :: OSI Approved :: MIT License
Classifier: Operating System :: OS Independent
Classifier: Programming Language :: Python :: 3
Classifier: Programming Language :: Python :: 3.8
Classifier: Programming Language :: Python :: 3.9
Classifier: Programming Language :: Python :: 3.10
Classifier: Programming Language :: Python :: 3.11
Classifier: Topic :: Multimedia :: Sound/Audio
Classifier: Topic :: Internet :: WWW/HTTP :: Indexing/Search
Requires-Python: >=3.8
License-File: LICENSE
Requires-Dist: yt-dlp>=2023.7.6
Requires-Dist: google-api-python-client>=2.95.0
Requires-Dist: google-auth-httplib2>=0.1.0
Requires-Dist: google-auth-oauthlib>=1.0.0
Requires-Dist: click>=8.1.0
Requires-Dist: rich>=13.4.0
Requires-Dist: colorama>=0.4.6
Requires-Dist: pydantic>=2.0.0
Requires-Dist: pydantic-settings>=2.0.0
Requires-Dist: toml>=0.10.2
Requires-Dist: tomli-w>=1.0.0
Requires-Dist: watchdog>=3.0.0
Requires-Dist: static-ffmpeg>=2.0
Requires-Dist: cryptography>=41.0.0
Provides-Extra: dev
Requires-Dist: pytest>=7.4.0; extra == "dev"
Requires-Dist: pytest-cov>=4.1.0; extra == "dev"
Requires-Dist: black>=23.0.0; extra == "dev"
Requires-Dist: flake8>=6.0.0; extra == "dev"
Requires-Dist: mypy>=1.5.0; extra == "dev"
Dynamic: license-file
